tentalog/__init__.py
tentalog/default_configuration.yaml
tentalog-0.2.1.dist-info/LICENSE
tentalog-0.2.1.dist-info/METADATA
tentalog-0.2.1.dist-info/WHEEL
tentalog-0.2.1.dist-info/top_level.txt
tentalog-0.2.1.dist-info/RECORD
