Metadata-Version: 2.1
Name: tentalog
Version: 0.2.1
Summary: Utility package for logging in Python
Home-page: https://github.com/nextblu/tentalog
Author: NextBlu
Author-email: hello@nextblu.com
License: MIT
Platform: UNKNOWN
Requires-Python: >=3.6.0
Requires-Dist: certifi (==2020.4.5.1)
Requires-Dist: chardet (==3.0.4)
Requires-Dist: coloredlogs (==14.0)
Requires-Dist: humanfriendly (==7.1.1)
Requires-Dist: idna (==2.9)
Requires-Dist: pyreadline (==2.1)
Requires-Dist: PyYAML (==5.3)
Requires-Dist: requests (==2.23.0)
Requires-Dist: urllib3 (==1.24.3)
